swarmauri_certservice_aws_kms/AwsKmsCertService.py
swarmauri_certservice_aws_kms/__init__.py
swarmauri_certservice_aws_kms-0.3.0.dev4.dist-info/METADATA
swarmauri_certservice_aws_kms-0.3.0.dev4.dist-info/WHEEL
swarmauri_certservice_aws_kms-0.3.0.dev4.dist-info/entry_points.txt
swarmauri_certservice_aws_kms-0.3.0.dev4.dist-info/RECORD
