Metadata-Version: 2.3
Name: swarmauri_certservice_aws_kms
Version: 0.3.0.dev4
Summary: AWS KMS backed CertService for Swarmauri
License: Apache-2.0
Author: Swarmauri
Author-email: opensource@swarmauri.com
Requires-Python: >=3.10,<3.13
Classifier: License :: OSI Approved :: Apache Software License
Classifier: Programming Language :: Python :: 3.10
Classifier: Programming Language :: Python :: 3.11
Classifier: Programming Language :: Python :: 3.12
Provides-Extra: docs
Provides-Extra: perf
Requires-Dist: asn1crypto
Requires-Dist: boto3 (>=1.28.0)
Requires-Dist: cryptography
Requires-Dist: mkdocs ; extra == "docs"
Requires-Dist: pytest-benchmark (>=4.0.0) ; extra == "perf"
Requires-Dist: swarmauri_base
Requires-Dist: swarmauri_core
Requires-Dist: swarmauri_standard
